ChangeCoordinate/__init__.py
ChangeCoordinate/change_coordinate.py
ChangeCoordinate-1.1.dist-info/LICENSE
ChangeCoordinate-1.1.dist-info/METADATA
ChangeCoordinate-1.1.dist-info/WHEEL
ChangeCoordinate-1.1.dist-info/top_level.txt
ChangeCoordinate-1.1.dist-info/RECORD
